cfxdb/__init__.py
cfxdb/_exception.py
cfxdb/_version.py
cfxdb/arealm.fbs
cfxdb/common.fbs
cfxdb/common.py
cfxdb/cookiestore.fbs
cfxdb/exporter.py
cfxdb/globalschema.py
cfxdb/log.fbs
cfxdb/meta.fbs
cfxdb/mrealm.fbs
cfxdb/mrealmschema.py
cfxdb/realmstore.fbs
cfxdb/reflection.fbs
cfxdb/tracing.py
cfxdb/usage.py
cfxdb/user.fbs
cfxdb/xbr.fbs
cfxdb/xbrmm.fbs
cfxdb/xbrnetwork.fbs
cfxdb/cookiestore/__init__.py
cfxdb/cookiestore/_cookie.py
cfxdb/cookiestore/_schema.py
cfxdb/gen/KeyValue.py
cfxdb/gen/ObjRef.py
cfxdb/gen/__init__.py
cfxdb/gen/arealm.bfbs
cfxdb/gen/common.bfbs
cfxdb/gen/cookiestore.bfbs
cfxdb/gen/log.bfbs
cfxdb/gen/meta.bfbs
cfxdb/gen/mrealm.bfbs
cfxdb/gen/oid_t.py
cfxdb/gen/realmstore.bfbs
cfxdb/gen/reflection.bfbs
cfxdb/gen/user.bfbs
cfxdb/gen/xbr.bfbs
cfxdb/gen/xbrmm.bfbs
cfxdb/gen/xbrnetwork.bfbs
cfxdb/gen/arealm/ApplicationRealm.py
cfxdb/gen/arealm/ApplicationRealmRole.py
cfxdb/gen/arealm/ApplicationRealmStatus.py
cfxdb/gen/arealm/AuthenticationMethod.py
cfxdb/gen/arealm/Credential.py
cfxdb/gen/arealm/MatchType.py
cfxdb/gen/arealm/Permission.py
cfxdb/gen/arealm/Principal.py
cfxdb/gen/arealm/Role.py
cfxdb/gen/arealm/UriCheckLevel.py
cfxdb/gen/arealm/__init__.py
cfxdb/gen/cookiestore/Cookie.py
cfxdb/gen/cookiestore/__init__.py
cfxdb/gen/log/IpVersion.py
cfxdb/gen/log/MNodeLog.py
cfxdb/gen/log/MNodeSession.py
cfxdb/gen/log/MNodeState.py
cfxdb/gen/log/MRealmRun.py
cfxdb/gen/log/MRealmState.py
cfxdb/gen/log/MWorkerLog.py
cfxdb/gen/log/MWorkerState.py
cfxdb/gen/log/MWorkerType.py
cfxdb/gen/log/MasterNodeUsage.py
cfxdb/gen/log/MasterNodeUsageStatus.py
cfxdb/gen/log/MasterRun.py
cfxdb/gen/log/MasterState.py
cfxdb/gen/log/__init__.py
cfxdb/gen/meta/Attribute.py
cfxdb/gen/meta/Comment.py
cfxdb/gen/meta/Doc.py
cfxdb/gen/meta/DocFormat.py
cfxdb/gen/meta/Reaction.py
cfxdb/gen/meta/Tag.py
cfxdb/gen/meta/TagDefinition.py
cfxdb/gen/meta/__init__.py
cfxdb/gen/mrealm/ClusterNodeMembership.py
cfxdb/gen/mrealm/ClusterStatus.py
cfxdb/gen/mrealm/ManagementRealm.py
cfxdb-25.12.2.dist-info/METADATA
cfxdb-25.12.2.dist-info/WHEEL
cfxdb-25.12.2.dist-info/licenses/LICENSE
cfxdb-25.12.2.dist-info/RECORD
